bitskins/__init__.py
bitskins/bitskins.py
bitskins-1.0.0.dist-info/LICENSE.txt
bitskins-1.0.0.dist-info/METADATA
bitskins-1.0.0.dist-info/WHEEL
bitskins-1.0.0.dist-info/top_level.txt
bitskins-1.0.0.dist-info/RECORD
