Metadata-Version: 2.1
Name: bitskins
Version: 1.0.0
Summary: Simple BitSkins API Wrapper
Home-page: https://github.com/Spacerulerwill/bitskins.py
Author: William Redding
Author-email: williamdredding@gmail.com
License: zlib/libpng
Keywords: api
Classifier: Development Status :: 5 - Production/Stable
Classifier: Operating System :: Microsoft :: Windows :: Windows 10
Classifier: License :: OSI Approved :: zlib/libpng License
Classifier: Programming Language :: Python :: 3
License-File: LICENSE.txt
